pylts/__init__.py
pylts/__main__.py
pylts/aws.py
pylts/cli.py
pylts-0.0.9.dist-info/METADATA
pylts-0.0.9.dist-info/WHEEL
pylts-0.0.9.dist-info/RECORD
